beeswax_wrapper/__init__.py
beeswax_wrapper/core/__init__.py
beeswax_wrapper/core/base_classes.py
beeswax_wrapper/core/beeswax.py
beeswax_wrapper/core/exceptions.py
beeswax_wrapper/credentials/__init__.py
beeswax_wrapper/credentials/credential_manager.py
beeswax_wrapper/modules/__init__.py
beeswax_wrapper/modules/account.py
beeswax_wrapper/modules/admin.py
beeswax_wrapper/modules/creatives.py
beeswax_wrapper/modules/extensions.py
beeswax_wrapper/modules/monitoring.py
beeswax_wrapper/modules/operations.py
beeswax_wrapper/modules/segments.py
beeswax_wrapper-1.0.1.dist-info/METADATA
beeswax_wrapper-1.0.1.dist-info/RECORD
beeswax_wrapper-1.0.1.dist-info/WHEEL
beeswax_wrapper-1.0.1.dist-info/top_level.txt
